simple_sugar/__init__.py
simple_sugar/simple_sugar.py
test/__init__.py
test/test_cases.py
simple_sugar-1.0.0.dist-info/LICENSE
simple_sugar-1.0.0.dist-info/METADATA
simple_sugar-1.0.0.dist-info/WHEEL
simple_sugar-1.0.0.dist-info/top_level.txt
simple_sugar-1.0.0.dist-info/RECORD
