Metadata-Version: 2.1
Name: simple-sugar
Version: 1.0.0
Summary: Syntactic sugar for beginners!
Home-page: https://github.com/jmoseley99/simple_sugar
Author: Jacob Moseley
Author-email: jm01295@surrey.ac.uk
License: MIT
Platform: UNKNOWN
Classifier: License :: OSI Approved :: MIT License
Classifier: Programming Language :: Python :: 3
Classifier: Programming Language :: Python :: 3.9
License-File: LICENSE
